code_extractor/__init__.py
code_extractor/__main__.py
code_extractor/extractor.py
code_extractor/file_reader.py
code_extractor/languages.py
code_extractor/models.py
code_extractor/search_engine.py
code_extractor/server.py
code_extractor/url_fetcher.py
code_extractor/vcs/__init__.py
code_extractor/vcs/factory.py
code_extractor/vcs/git.py
mcp_server_code_extractor-0.4.2.dist-info/METADATA
mcp_server_code_extractor-0.4.2.dist-info/WHEEL
mcp_server_code_extractor-0.4.2.dist-info/entry_points.txt
mcp_server_code_extractor-0.4.2.dist-info/top_level.txt
mcp_server_code_extractor-0.4.2.dist-info/RECORD
